SemiSegAPI
