Metadata-Version: 2.1
Name: semisup-segmentation
Version: 0.0.102
Summary: API that provides methods to construct deep segmentation models using semi-supervised methods.
Home-page: https://github.com/adines/SemiSeg
Author: Adrian Ines
Author-email: adines@unirioja.es
License: UNKNOWN
Keywords: segmentation,deep learning,semi-supervised
Platform: UNKNOWN
Classifier: Development Status :: 4 - Beta
Classifier: Intended Audience :: Developers
Classifier: Topic :: Software Development :: Build Tools
Classifier: License :: OSI Approved :: MIT License
Classifier: Programming Language :: Python :: 3.6
License-File: LICENSE.txt
